{
	"message": "success",
	"status": 200,
	"data": {
		"list1": [
			{"title":"留学的理由", "date":"2017-12-20"},
			{"title":"魅力城市", "date":"2017-12-20"},
			{"title":"天津人才引进规定...", "date":"2017-12-20"},
			{"title":"世界宜居之选", "date":"2017-12-20"},
			{"title":"中国海归人才需求趋势", "date":"2017-12-20"},
			{"title":"国际多元文化", "date":"2017-12-20"}
		],
		"list2": [
			{"title":"华盛顿大华府校友会举办”双节“聚会", "date":"2017-12-20"},
			{"title":"世界校友代表大会”中部崛起-院士专题讲座“", "date":"2017-12-20"},
			{"title":"天津大学扬州校友会组织金秋游园活动", "date":"2017-12-20"},
			{"title":"毕业50年校友班捐资600万设立北洋奖学金", "date":"2017-12-20"},
			{"title":"扬“校风助天大 驭”州“车奔一流", "date":"2017-12-20"},
			{"title":"健康与安全", "date":"2017-12-20"}
		],
		"list3": [
			{"title":"2017年度中外合作办学项目评估公示", "date":"2017-12-20"},
			{"title":"2017津台大学生”海河情“", "date":"2017-12-20"},
			{"title":"天津文化", "date":"2017-12-20"},
			{"title":"网络安全宣传周科技日：用高科技捍卫我们的网络安全", "date":"2017-12-20"},
			{"title":"“走进膜世界，分享膜神奇”主题活动", "date":"2017-12-20"},
			{"title":"中国留学生如何受益于美国本科转学生", "date":"2017-12-20"}
		],
		"list4": [
			{"title":"天津（中华人民共和国直辖市）", "date":"2017-12-20"},
			{"title":"天津风景", "date":"2017-12-20"}
		]
	}
}

